mutmut/__init__.py
mutmut/__main__.py
mutmut/file_mutation.py
mutmut/node_mutation.py
mutmut/result_browser_layout.tcss
mutmut/trampoline_templates.py
tests/__init__.py
tests/test_generation_error_handling.py
tests/test_mutation.py
tests/test_mutmut3.py
tests/e2e/__init__.py
tests/e2e/test_cli_version.py
tests/e2e/test_e2e_result_snapshots.py
mutmut-3.3.1.dist-info/AUTHORS.rst
mutmut-3.3.1.dist-info/LICENSE
mutmut-3.3.1.dist-info/METADATA
mutmut-3.3.1.dist-info/WHEEL
mutmut-3.3.1.dist-info/entry_points.txt
mutmut-3.3.1.dist-info/top_level.txt
mutmut-3.3.1.dist-info/RECORD
