Metadata-Version: 2.1
Name: mutmut
Version: 3.3.1
Summary: mutation testing for Python 3
Home-page: https://github.com/boxed/mutmut
Author: Anders Hovmöller
Author-email: boxed@killingar.net
License: BSD
Keywords: mutmut mutant mutation test testing
Classifier: Development Status :: 4 - Beta
Classifier: Intended Audience :: Developers
Classifier: License :: OSI Approved :: BSD License
Classifier: Natural Language :: English
Classifier: Programming Language :: Python :: 3
Classifier: Programming Language :: Python :: 3.7
License-File: LICENSE
License-File: AUTHORS.rst
Requires-Dist: libcst~=1.7.0
Requires-Dist: click
Requires-Dist: setproctitle
Requires-Dist: textual
Requires-Dist: toml>=0.10.2; python_version < "3.11"
Requires-Dist: pytest
